LICENSE
MANIFEST.in
README.rst
setup.py
ringbell/__init__.py
ringbell/__version__.py
ringbell/_auto_ringbell.py
ringbell/all_exceptions.py
ringbell/auto.py
ringbell/immediate.py
ringbell/ringbell.py
ringbell.egg-info/PKG-INFO
ringbell.egg-info/SOURCES.txt
ringbell.egg-info/dependency_links.txt
ringbell.egg-info/requires.txt
ringbell.egg-info/top_level.txt
ringbell/samples/bell.wav
ringbell/samples/bojack.wav
ringbell/samples/correct_answer.wav
ringbell/samples/happy_bells.wav
ringbell/samples/interface_hint.wav
ringbell/samples/microwave.wav
ringbell/samples/pink_guy.wav
ringbell/samples/positive_notification.wav
ringbell/samples/rick.wav
ringbell/samples/tile_game_reveal.wav
ringbell/samples/whale.wav
ringbell/samples/wrong_answer.wav
ringbell/utils/__init__.py
ringbell/utils/invisible_audio.py