Metadata-Version: 1.1
Name: ringbell
Version: 1.0.2
Summary: Python package to play a sound when a task completes.
Home-page: https://github.com/LucaCappelletti94/ringbell
Author: Luca Cappelletti
Author-email: cappelletti.luca94@gmail.com
License: MIT
Platform: UNKNOWN
Classifier: Development Status :: 3 - Alpha
Classifier: License :: OSI Approved :: MIT License
Classifier: Programming Language :: Python :: 3
